LICENSE.md
MANIFEST.in
README.md
setup.cfg
setup.py
lineedit/__init__.py
lineedit/buffer.py
lineedit/history.py
lineedit/prompt.py
lineedit.egg-info/PKG-INFO
lineedit.egg-info/SOURCES.txt
lineedit.egg-info/dependency_links.txt
lineedit.egg-info/requires.txt
lineedit.egg-info/top_level.txt
lineedit/deps/LICENSE
lineedit/deps/__init__.py
lineedit/deps/prompt_toolkit/__init__.py
lineedit/deps/prompt_toolkit/auto_suggest.py
lineedit/deps/prompt_toolkit/buffer.py
lineedit/deps/prompt_toolkit/cache.py
lineedit/deps/prompt_toolkit/document.py
lineedit/deps/prompt_toolkit/enums.py
lineedit/deps/prompt_toolkit/history.py
lineedit/deps/prompt_toolkit/keys.py
lineedit/deps/prompt_toolkit/log.py
lineedit/deps/prompt_toolkit/mouse_events.py
lineedit/deps/prompt_toolkit/patch_stdout.py
lineedit/deps/prompt_toolkit/renderer.py
lineedit/deps/prompt_toolkit/search.py
lineedit/deps/prompt_toolkit/selection.py
lineedit/deps/prompt_toolkit/token.py
lineedit/deps/prompt_toolkit/utils.py
lineedit/deps/prompt_toolkit/validation.py
lineedit/deps/prompt_toolkit/win32_types.py
lineedit/deps/prompt_toolkit/application/__init__.py
lineedit/deps/prompt_toolkit/application/application.py
lineedit/deps/prompt_toolkit/application/current.py
lineedit/deps/prompt_toolkit/application/dummy.py
lineedit/deps/prompt_toolkit/application/run_in_terminal.py
lineedit/deps/prompt_toolkit/clipboard/__init__.py
lineedit/deps/prompt_toolkit/clipboard/base.py
lineedit/deps/prompt_toolkit/clipboard/in_memory.py
lineedit/deps/prompt_toolkit/clipboard/pyperclip.py
lineedit/deps/prompt_toolkit/completion/__init__.py
lineedit/deps/prompt_toolkit/completion/base.py
lineedit/deps/prompt_toolkit/completion/filesystem.py
lineedit/deps/prompt_toolkit/completion/fuzzy_completer.py
lineedit/deps/prompt_toolkit/completion/word_completer.py
lineedit/deps/prompt_toolkit/contrib/__init__.py
lineedit/deps/prompt_toolkit/contrib/completers/__init__.py
lineedit/deps/prompt_toolkit/contrib/completers/system.py
lineedit/deps/prompt_toolkit/contrib/regular_languages/__init__.py
lineedit/deps/prompt_toolkit/contrib/regular_languages/compiler.py
