Metadata-Version: 2.1
Name: lineedit
Version: 0.1.6
Summary: An readline library based on prompt_toolkit which supports multiple modes
Home-page: https://github.com/randy3k/lineedit
Author: Randy Lai
License: UNKNOWN
Platform: UNKNOWN
Provides-Extra: test
